{
  "1000": {
    "name": "Test Tenant",
    "tag": []
  },
  "2095": {
    "name": "LowCode Async Integrator",
    "tag": [],
    "meta": {},
    "adminEmail": "demo",
    "owner": "Demo",
    "_cre": 1713077563302
  },
  "2103": {
    "name": "tmForum",
    "tag": [],
    "meta": {},
    "adminEmail": "demo",
    "owner": "Demo",
    "_cre": 1714106253411
  },
  "1000/DE": {
    "name": "Region Germany",
    "tag": [
      "region"
    ],
    "meta": {
      "SAP-tenant": "12345678/1"
    }
  },
  "1000/DE/Berlin": {
    "name": "City: Berlin",
    "tag": [
      "city",
      "capital",
      "huge"
    ],
    "meta": {
      "SAP-tenant": "12345678/2"
    }
  },
  "1000/DE/Hamburg": {
    "name": "City: Hamburg",
    "tag": [
      "city",
      "huge"
    ],
    "meta": {
      "SAP-tenant": "12345678/3"
    }
  },
  "1000/DE/Munich": {
    "name": "City: Munich",
    "tag": [
      "city",
      "huge"
    ],
    "meta": {
      "SAP-tenant": "12345678/4"
    }
  },
  "1000/DE/Essen": {
    "name": "City: Essen",
    "tag": [
      "city",
      "huge"
    ],
    "meta": {
      "SAP-tenant": "12345678/5"
    }
  },
  "1000/DE/Bochum": {
    "name": "City: Bochum",
    "tag": [
      "city",
      "mid"
    ],
    "meta": {
      "SAP-tenant": "12345678/6"
    }
  },
  "1000/DE/Hattingen": {
    "name": "City: Hattingen",
    "tag": [
      "city",
      "small"
    ],
    "meta": {
      "SAP-tenant": "12345678/7"
    }
  },
  "1000/UK": {
    "name": "UK",
    "tag": [
      "region"
    ]
  },
  "1000/DE/Bonn": {
    "name": "City: Bonn",
    "tag": [
      "city",
      "mid"
    ],
    "meta": {
      "SAP-tenant": "12345678/899"
    }
  }
}